<?xml version="1.0" encoding="utf-8"?>
<TextureAtlas imagePath="fatal-error-p3.png">
	<!-- Created with Adobe Animate version 22.0.7.214 -->
	<!-- http://www.adobe.com/products/animate.html -->
	<SubTexture name="fatal idle dance0000" x="0" y="0" width="300" height="300"/>
	<SubTexture name="fatal idle dance0001" x="0" y="0" width="300" height="300"/>
	<SubTexture name="fatal idle dance0002" x="300" y="0" width="300" height="300"/>
	<SubTexture name="fatal idle dance0003" x="300" y="0" width="300" height="300"/>
	<SubTexture name="fatal idle dance0004" x="600" y="0" width="300" height="300"/>
	<SubTexture name="fatal idle dance0005" x="600" y="0" width="300" height="300"/>
	<SubTexture name="fatal idle dance0006" x="900" y="0" width="300" height="300"/>
	<SubTexture name="fatal idle dance0007" x="900" y="0" width="300" height="300"/>
	<SubTexture name="fatal idle dance0008" x="1200" y="0" width="300" height="300"/>
	<SubTexture name="fatal idle dance0009" x="1200" y="0" width="300" height="300"/>
	<SubTexture name="fatal idle dance0010" x="1200" y="0" width="300" height="300"/>
	<SubTexture name="fatal idle dance0011" x="1200" y="0" width="300" height="300"/>
	<SubTexture name="fatal sing down0000" x="1500" y="0" width="300" height="300"/>
	<SubTexture name="fatal sing down0001" x="1500" y="0" width="300" height="300"/>
	<SubTexture name="fatal sing down0002" x="1800" y="0" width="300" height="300"/>
	<SubTexture name="fatal sing down0003" x="1800" y="0" width="300" height="300"/>
	<SubTexture name="fatal sing down0004" x="0" y="300" width="300" height="300"/>
	<SubTexture name="fatal sing down0005" x="0" y="300" width="300" height="300"/>
	<SubTexture name="fatal sing down0006" x="300" y="300" width="300" height="300"/>
	<SubTexture name="fatal sing down0007" x="300" y="300" width="300" height="300"/>
	<SubTexture name="fatal sing down0008" x="300" y="300" width="300" height="300"/>
	<SubTexture name="fatal sing down0009" x="300" y="300" width="300" height="300"/>
	<SubTexture name="fatal sing down0010" x="300" y="300" width="300" height="300"/>
	<SubTexture name="fatal sing down0011" x="300" y="300" width="300" height="300"/>
	<SubTexture name="fatal sing left0000" x="600" y="300" width="300" height="300"/>
	<SubTexture name="fatal sing left0001" x="600" y="300" width="300" height="300"/>
	<SubTexture name="fatal sing left0002" x="900" y="300" width="300" height="300"/>
	<SubTexture name="fatal sing left0003" x="900" y="300" width="300" height="300"/>
	<SubTexture name="fatal sing left0004" x="1200" y="300" width="300" height="300"/>
	<SubTexture name="fatal sing left0005" x="1200" y="300" width="300" height="300"/>
	<SubTexture name="fatal sing left0006" x="1500" y="300" width="300" height="300"/>
	<SubTexture name="fatal sing left0007" x="1500" y="300" width="300" height="300"/>
	<SubTexture name="fatal sing left0008" x="1500" y="300" width="300" height="300"/>
	<SubTexture name="fatal sing left0009" x="1500" y="300" width="300" height="300"/>
	<SubTexture name="fatal sing left0010" x="1500" y="300" width="300" height="300"/>
	<SubTexture name="fatal sing left0011" x="1500" y="300" width="300" height="300"/>
	<SubTexture name="fatal sing right0000" x="1800" y="300" width="300" height="300"/>
	<SubTexture name="fatal sing right0001" x="1800" y="300" width="300" height="300"/>
	<SubTexture name="fatal sing right0002" x="0" y="600" width="300" height="300"/>
	<SubTexture name="fatal sing right0003" x="0" y="600" width="300" height="300"/>
	<SubTexture name="fatal sing right0004" x="300" y="600" width="300" height="300"/>
	<SubTexture name="fatal sing right0005" x="300" y="600" width="300" height="300"/>
	<SubTexture name="fatal sing right0006" x="600" y="600" width="300" height="300"/>
	<SubTexture name="fatal sing right0007" x="600" y="600" width="300" height="300"/>
	<SubTexture name="fatal sing right0008" x="600" y="600" width="300" height="300"/>
	<SubTexture name="fatal sing right0009" x="600" y="600" width="300" height="300"/>
	<SubTexture name="fatal sing right0010" x="600" y="600" width="300" height="300"/>
	<SubTexture name="fatal sing right0011" x="600" y="600" width="300" height="300"/>
	<SubTexture name="fatal sing up0000" x="900" y="600" width="300" height="300"/>
	<SubTexture name="fatal sing up0001" x="900" y="600" width="300" height="300"/>
	<SubTexture name="fatal sing up0002" x="1200" y="600" width="300" height="300"/>
	<SubTexture name="fatal sing up0003" x="1200" y="600" width="300" height="300"/>
	<SubTexture name="fatal sing up0004" x="1500" y="600" width="300" height="300"/>
	<SubTexture name="fatal sing up0005" x="1500" y="600" width="300" height="300"/>
	<SubTexture name="fatal sing up0006" x="1800" y="600" width="300" height="300"/>
	<SubTexture name="fatal sing up0007" x="1800" y="600" width="300" height="300"/>
	<SubTexture name="fatal sing up0008" x="1800" y="600" width="300" height="300"/>
	<SubTexture name="fatal sing up0009" x="1800" y="600" width="300" height="300"/>
	<SubTexture name="fatal sing up0010" x="1800" y="600" width="300" height="300"/>
	<SubTexture name="fatal sing up0011" x="1800" y="600" width="300" height="300"/>
</TextureAtlas>
